mv_laplace/MvLaplaceSampler.py
mv_laplace/__init__.py
mv_laplace-0.1.1.dist-info/LICENSE
mv_laplace-0.1.1.dist-info/METADATA
mv_laplace-0.1.1.dist-info/WHEEL
mv_laplace-0.1.1.dist-info/top_level.txt
mv_laplace-0.1.1.dist-info/RECORD
