Metadata-Version: 2.1
Name: mv-laplace
Version: 0.1.1
Summary: Multivariate Laplace Distribution Sampler
Home-page: https://github.com/Calvinxc1/mv-laplace
Author: Jason M. Cherry
Author-email: jcherry@gmail.com
License: UNKNOWN
Platform: UNKNOWN
Classifier: Development Status :: 3 - Alpha
Classifier: License :: OSI Approved :: GNU General Public License (GPL)
Classifier: Programming Language :: Python :: 3
Requires-Python: >=3.10, <4
License-File: LICENSE
Requires-Dist: numpy (<2,>=1.20)
Requires-Dist: scipy (<2,>=1.7)
